mvsr/__init__.py
mvsr/libmvsr.py
mvsr/mvsr.py
mvsr/py.typed
mvsr/lib/libmvsr.dll
mvsr-0.2.2.dist-info/METADATA
mvsr-0.2.2.dist-info/WHEEL
mvsr-0.2.2.dist-info/RECORD
