Metadata-Version: 2.4
Name: mvsr
Version: 0.2.2
Summary: Library for Fast Segmented Regression
Project-URL: Repository, https://github.com/Loesgar/mvsr
Project-URL: Documentation, https://loesgar.github.io/mvsr/stable/lang/python/
Classifier: Development Status :: 4 - Beta
Classifier: License :: OSI Approved :: Mozilla Public License 2.0 (MPL 2.0)
Classifier: Operating System :: MacOS
Classifier: Operating System :: Microsoft :: Windows
Classifier: Operating System :: Unix
Classifier: Programming Language :: C++
Classifier: Programming Language :: Python :: 3
Classifier: Topic :: Scientific/Engineering :: Information Analysis
Classifier: Typing :: Typed
Requires-Python: >=3.10
Requires-Dist: numpy>=1.21
Provides-Extra: matplotlib
Requires-Dist: matplotlib>=3.5; extra == 'matplotlib'
